moutamadris_api/__init__.py
moutamadris_api/api.py
moutamadris_api/main.py
moutamadris_api/moutamadris_classes.py
moutamadris_api/moutamadris_constants.py
moutamadris_api/moutamadris_enums.py
moutamadris_api-1.0.dist-info/METADATA
moutamadris_api-1.0.dist-info/WHEEL
moutamadris_api-1.0.dist-info/top_level.txt
moutamadris_api-1.0.dist-info/RECORD
