Metadata-Version: 2.1
Name: moutamadris-api
Version: 1.0
Summary: This package provides an interface for interacting with the Moutamadris API. Moutamadris is a platform used by Moroccan students to access educational resources, track academic progress, and manage their accounts. This package allows developers to programmatically access these features, making it easier to integrate Moutamadris functionalities into their own applications.
Author: Abdellah Elidrissi
Requires-Dist: requests >=2.32.3
Requires-Dist: beautifulsoup4 >=4.12.3
